GcodeTools/__init__.py
GcodeTools/gcode.py
GcodeTools/gcode_parser.py
GcodeTools/gcode_tools.py
GcodeTools/gcode_types.py
gcodetools-0.2.3.dist-info/METADATA
gcodetools-0.2.3.dist-info/WHEEL
gcodetools-0.2.3.dist-info/licenses/LICENSE
gcodetools-0.2.3.dist-info/RECORD
