Metadata-Version: 2.4
Name: GcodeTools
Version: 0.2.3
Summary: Python G-Code Tools library with complete G-Code Reader and Writer
Project-URL: Homepage, https://github.com/matszwe02/GcodeTools
Project-URL: Issues, https://github.com/matszwe02/GcodeTools/issues
License-Expression: MIT
License-File: LICENSE
Keywords: 3d,g-code,gcode,printing
Classifier: Development Status :: 4 - Beta
Classifier: Intended Audience :: Developers
Classifier: Operating System :: OS Independent
Classifier: Programming Language :: Python :: 3
Requires-Python: >=3.8
